ntnx_monitoring_py_client/__init__.py
ntnx_monitoring_py_client/api_client.py
ntnx_monitoring_py_client/api_response.py
ntnx_monitoring_py_client/configuration.py
ntnx_monitoring_py_client/custom_retry.py
ntnx_monitoring_py_client/rest.py
ntnx_monitoring_py_client/api/__init__.py
ntnx_monitoring_py_client/api/alert_email_configuration_api.py
ntnx_monitoring_py_client/api/alerts_api.py
ntnx_monitoring_py_client/api/audits_api.py
ntnx_monitoring_py_client/api/cluster_logs_api.py
ntnx_monitoring_py_client/api/events_api.py
ntnx_monitoring_py_client/api/manage_alerts_api.py
ntnx_monitoring_py_client/api/system_defined_checks_api.py
ntnx_monitoring_py_client/api/system_defined_policies_api.py
ntnx_monitoring_py_client/api/user_defined_policies_api.py
ntnx_monitoring_py_client/models/__init__.py
ntnx_monitoring_py_client/models/OneOfcommon/__init__.py
ntnx_monitoring_py_client/models/OneOfcommon/v1/__init__.py
ntnx_monitoring_py_client/models/OneOfcommon/v1/config/KVPairvalue.py
ntnx_monitoring_py_client/models/OneOfcommon/v1/config/__init__.py
ntnx_monitoring_py_client/models/OneOfmonitoring/__init__.py
ntnx_monitoring_py_client/models/OneOfmonitoring/v4/__init__.py
ntnx_monitoring_py_client/models/OneOfmonitoring/v4/common/MetricDetailmetric_value.py
ntnx_monitoring_py_client/models/OneOfmonitoring/v4/common/MetricDetailthreshold_value.py
ntnx_monitoring_py_client/models/OneOfmonitoring/v4/common/Parameterparam_value.py
ntnx_monitoring_py_client/models/OneOfmonitoring/v4/common/__init__.py
ntnx_monitoring_py_client/models/OneOfmonitoring/v4/error/ErrorResponseerror.py
ntnx_monitoring_py_client/models/OneOfmonitoring/v4/error/__init__.py
ntnx_monitoring_py_client/models/OneOfmonitoring/v4/serviceability/AlertPolicyConfigurableParameterparam_value.py
ntnx_monitoring_py_client/models/OneOfmonitoring/v4/serviceability/ArchiveOptsupload_params.py
ntnx_monitoring_py_client/models/OneOfmonitoring/v4/serviceability/CollectLogsApiResponsedata.py
ntnx_monitoring_py_client-4.2.1.dist-info/LICENSE.txt
ntnx_monitoring_py_client-4.2.1.dist-info/METADATA
ntnx_monitoring_py_client-4.2.1.dist-info/WHEEL
ntnx_monitoring_py_client-4.2.1.dist-info/top_level.txt
ntnx_monitoring_py_client-4.2.1.dist-info/RECORD
